{
  "encyclopedias": [
    {
      "slug": "plant-taxonomy-letter-kor-2",
      "titleTh": "อนุกรมวิธานพืช อักษร ก (พิมพ์ครั้งที่ ๒)",
      "titleEn": "Plant Taxonomy — Letter Kor (2nd ed.)",
      "description": "สรุปย่อและเชื่อมโยงบทความจาก สารานุกรม อนุกรมวิธานพืช อักษร ก (พิมพ์ครั้งที่ ๒) โดยอ้างอิงจาก LST Encyclopedia",
      "sourceUrl": "https://lst.nectec.or.th/encyclopedia/",
      "publisher": "NECTEC LST",
      "language": "th",
      "tags": ["อนุกรมวิธานพืช", "อักษร ก", "พืช"],
      "meta": { "source": "LST Encyclopedia", "note": "ข้อมูลย่อสำหรับ seed" },
      "articles": [
        {
          "slug": "lindsaea-chienii",
          "titleTh": "กูดหางนกยูง — Lindsaea chienii Ching",
          "summary": "เฟิร์นพื้นดิน ใบแบบขนนกสองชั้น; ชื่อวิทยาศาสตร์ Lindsaea chienii (วงศ์ Lindsaeaceae)",
          "externalUrl": "https://lst.nectec.or.th/encyclopedia/wikipedia/plant_taxonomy/view/index.php?cid=469&namelink=%E0%B8%81%E0%B8%B9%E0%B8%94%E0%B8%AB%E0%B8%B2%E0%B8%87%E0%B8%99%E0%B8%81%E0%B8%A2%E0%B8%B9%E0%B8%87",
          "contentHtml": "<p><strong>กูดหางนกยูง</strong> (Lindsaea chienii) เป็นเฟิร์นในวงศ์ Lindsaeaceae พบบนดินในป่าชื้น ใบประกอบแบบขนนกสองชั้น</p>",
          "keywords": ["เฟิร์น", "Lindsaea", "Lindsaeaceae"]
        },
        {
          "slug": "colysis-hemionitidea",
          "titleTh": "กูดหางนกกะลิง — Colysis hemionitidea (Wall. ex Kunze) Bosman",
          "summary": "เฟิร์นวงศ์ Polypodiaceae; ใบรูปไข่ยาว ก้านใบเรียว",
          "externalUrl": "https://lst.nectec.or.th/encyclopedia/wikipedia/plant_taxonomy/view/index.php?cid=45&namelink=%E0%B8%81%E0%B8%B9%E0%B8%94%E0%B8%AB%E0%B8%B2%E0%B8%87%E0%B8%99%E0%B8%81%E0%B8%81%E0%B8%B0%E0%B8%A5%E0%B8%B4%E0%B8%87",
          "contentHtml": "<p><strong>กูดหางนกกะลิง</strong> (Colysis hemionitidea) อยู่ในวงศ์ Polypodiaceae พบตามโขดหินหรือพื้นที่ชื้น</p>",
          "keywords": ["เฟิร์น", "Colysis", "Polypodiaceae"]
        },
        {
          "slug": "cinnamomum-tamala",
          "titleTh": "แกง — Cinnamomum tamala Nees & Eberm.",
          "summary": "ไม้ต้นวงศ์ Lauraceae ใบเรียงตรงข้าม มีเส้นใบคู่ขนานเด่นชัด",
          "externalUrl": "https://lst.nectec.or.th/encyclopedia/wikipedia/plant_taxonomy/view/index.php?cid=499&namelink=%E0%B9%81%E0%B8%81%E0%B8%87",
          "contentHtml": "<p><strong>แกง</strong> (Cinnamomum tamala) อยู่ในวงศ์ Lauraceae ใช้เป็นเครื่องเทศในบางภูมิภาค</p>",
          "keywords": ["Cinnamomum", "Lauraceae", "พฤกษศาสตร์"]
        }
      ]
    }
  ]
}